CHANGELOG.txt
LICENCE.txt
MANIFEST.in
README.txt
setup.py
pubsame/__init__.py
pubsame.egg-info/PKG-INFO
pubsame.egg-info/SOURCES.txt
pubsame.egg-info/dependency_links.txt
pubsame.egg-info/requires.txt
pubsame.egg-info/top_level.txt
venu/Lib/site-packages/_distutils_hack/__init__.py
venu/Lib/site-packages/_distutils_hack/override.py
venu/Lib/site-packages/pip/__init__.py
venu/Lib/site-packages/pip/__main__.py
venu/Lib/site-packages/pip/__pip-runner__.py
venu/Lib/site-packages/pip-22.2.1.dist-info/LICENSE.txt
venu/Lib/site-packages/pip-22.2.1.dist-info/entry_points.txt
venu/Lib/site-packages/pip-22.2.1.dist-info/top_level.txt
venu/Lib/site-packages/pip/_internal/__init__.py
venu/Lib/site-packages/pip/_internal/build_env.py
venu/Lib/site-packages/pip/_internal/cache.py
venu/Lib/site-packages/pip/_internal/configuration.py
venu/Lib/site-packages/pip/_internal/exceptions.py
venu/Lib/site-packages/pip/_internal/main.py
venu/Lib/site-packages/pip/_internal/pyproject.py
venu/Lib/site-packages/pip/_internal/self_outdated_check.py
venu/Lib/site-packages/pip/_internal/wheel_builder.py
venu/Lib/site-packages/pip/_internal/cli/__init__.py
venu/Lib/site-packages/pip/_internal/cli/autocompletion.py
venu/Lib/site-packages/pip/_internal/cli/base_command.py
venu/Lib/site-packages/pip/_internal/cli/cmdoptions.py
venu/Lib/site-packages/pip/_internal/cli/command_context.py
venu/Lib/site-packages/pip/_internal/cli/main.py
venu/Lib/site-packages/pip/_internal/cli/main_parser.py
venu/Lib/site-packages/pip/_internal/cli/parser.py
venu/Lib/site-packages/pip/_internal/cli/progress_bars.py
venu/Lib/site-packages/pip/_internal/cli/req_command.py
venu/Lib/site-packages/pip/_internal/cli/spinners.py
venu/Lib/site-packages/pip/_internal/cli/status_codes.py
venu/Lib/site-packages/pip/_internal/commands/__init__.py
venu/Lib/site-packages/pip/_internal/commands/cache.py
venu/Lib/site-packages/pip/_internal/commands/check.py
venu/Lib/site-packages/pip/_internal/commands/completion.py
venu/Lib/site-packages/pip/_internal/commands/configuration.py
venu/Lib/site-packages/pip/_internal/commands/debug.py
venu/Lib/site-packages/pip/_internal/commands/download.py
venu/Lib/site-packages/pip/_internal/commands/freeze.py
venu/Lib/site-packages/pip/_internal/commands/hash.py
venu/Lib/site-packages/pip/_internal/commands/help.py
venu/Lib/site-packages/setuptools-63.2.0.dist-info/entry_points.txt
venu/Lib/site-packages/setuptools-63.2.0.dist-info/top_level.txt
